<?xml version="1.0" encoding="UTF-8"?>
<GenRun Id="synth_1" LaunchPart="xc7a200tfbg676-2" LaunchTime="1552114097">
  <File Type="PA-TCL" Name="single_cycle_cpu_display.tcl"/>
  <File Type="REPORTS-TCL" Name="single_cycle_cpu_display_reports.tcl"/>
  <File Type="RDS-RDS" Name="single_cycle_cpu_display.vds"/>
  <File Type="RDS-UTIL" Name="single_cycle_cpu_display_utilization_synth.rpt"/>
  <File Type="RDS-UTIL-PB" Name="single_cycle_cpu_display_utilization_synth.pb"/>
  <File Type="RDS-DCP" Name="single_cycle_cpu_display.dcp"/>
  <FileSet Name="sources" Type="DesignSrcs" RelSrcDir="$PSRCDIR/sources_1">
    <Filter Type="Srcs"/>
    <File Path="$PSRCDIR/sources_1/imports/LS_CPU_LAB/lcd_module.dcp">
      <FileInfo>
        <Attr Name="ImportPath" Val="$PPRDIR/../../../trialley/Desktop/LS_CPU_LAB/lcd_module.dcp"/>
        <Attr Name="ImportTime" Val="1486695670"/>
        <Attr Name="UsedIn" Val="synthesis"/>
        <Attr Name="UsedIn" Val="implementation"/>
      </FileInfo>
    </File>
    <File Path="$PSRCDIR/sources_1/imports/LS_CPU_LAB/6_single_cycle_cpu/adder.v">
      <FileInfo>
        <Attr Name="ImportPath" Val="$PPRDIR/../../../trialley/Desktop/LS_CPU_LAB/6_single_cycle_cpu/adder.v"/>
        <Attr Name="ImportTime" Val="1486602986"/>
        <Attr Name="UsedIn" Val="synthesis"/>
        <Attr Name="UsedIn" Val="implementation"/>
        <Attr Name="UsedIn" Val="simulation"/>
      </FileInfo>
    </File>
    <File Path="$PSRCDIR/sources_1/imports/LS_CPU_LAB/6_single_cycle_cpu/alu.v">
      <FileInfo>
        <Attr Name="ImportPath" Val="$PPRDIR/../../../trialley/Desktop/LS_CPU_LAB/6_single_cycle_cpu/alu.v"/>
        <Attr Name="ImportTime" Val="1486602986"/>
        <Attr Name="UsedIn" Val="synthesis"/>
        <Attr Name="UsedIn" Val="implementation"/>
        <Attr Name="UsedIn" Val="simulation"/>
      </FileInfo>
    </File>
    <File Path="$PSRCDIR/sources_1/imports/LS_CPU_LAB/6_single_cycle_cpu/data_ram.v">
      <FileInfo>
        <Attr Name="ImportPath" Val="$PPRDIR/../../../trialley/Desktop/LS_CPU_LAB/6_single_cycle_cpu/data_ram.v"/>
        <Attr Name="ImportTime" Val="1486602986"/>
        <Attr Name="UsedIn" Val="synthesis"/>
        <Attr Name="UsedIn" Val="implementation"/>
        <Attr Name="UsedIn" Val="simulation"/>
      </FileInfo>
    </File>
    <File Path="$PSRCDIR/sources_1/imports/LS_CPU_LAB/6_single_cycle_cpu/inst_rom.v">
      <FileInfo>
        <Attr Name="ImportPath" Val="$PPRDIR/../../../trialley/Desktop/LS_CPU_LAB/6_single_cycle_cpu/inst_rom.v"/>
        <Attr Name="ImportTime" Val="1486602986"/>
        <Attr Name="UsedIn" Val="synthesis"/>
        <Attr Name="UsedIn" Val="implementation"/>
        <Attr Name="UsedIn" Val="simulation"/>
      </FileInfo>
    </File>
    <File Path="$PSRCDIR/sources_1/imports/LS_CPU_LAB/6_single_cycle_cpu/regfile.v">
      <FileInfo>
        <Attr Name="ImportPath" Val="$PPRDIR/../../../trialley/Desktop/LS_CPU_LAB/6_single_cycle_cpu/regfile.v"/>
        <Attr Name="ImportTime" Val="1486602986"/>
        <Attr Name="UsedIn" Val="synthesis"/>
        <Attr Name="UsedIn" Val="implementation"/>
        <Attr Name="UsedIn" Val="simulation"/>
      </FileInfo>
    </File>
    <File Path="$PSRCDIR/sources_1/imports/LS_CPU_LAB/6_single_cycle_cpu/single_cycle_cpu.v">
      <FileInfo>
        <Attr Name="ImportPath" Val="$PPRDIR/../../../trialley/Desktop/LS_CPU_LAB/6_single_cycle_cpu/single_cycle_cpu.v"/>
        <Attr Name="ImportTime" Val="1486602986"/>
        <Attr Name="UsedIn" Val="synthesis"/>
        <Attr Name="UsedIn" Val="implementation"/>
        <Attr Name="UsedIn" Val="simulation"/>
      </FileInfo>
    </File>
    <File Path="$PSRCDIR/sources_1/imports/LS_CPU_LAB/6_single_cycle_cpu/single_cycle_cpu_display.v">
      <FileInfo>
        <Attr Name="ImportPath" Val="$PPRDIR/../../../trialley/Desktop/LS_CPU_LAB/6_single_cycle_cpu/single_cycle_cpu_display.v"/>
        <Attr Name="ImportTime" Val="1486602986"/>
        <Attr Name="UsedIn" Val="synthesis"/>
        <Attr Name="UsedIn" Val="implementation"/>
        <Attr Name="UsedIn" Val="simulation"/>
      </FileInfo>
    </File>
    <Config>
      <Option Name="DesignMode" Val="RTL"/>
      <Option Name="TopModule" Val="single_cycle_cpu_display"/>
      <Option Name="TopAutoSet" Val="TRUE"/>
    </Config>
  </FileSet>
  <FileSet Name="constrs_in" Type="Constrs" RelSrcDir="$PSRCDIR/constrs_1">
    <Filter Type="Constrs"/>
    <File Path="$PSRCDIR/constrs_1/imports/6_single_cycle_cpu/single_cycle_cpu.xdc">
      <FileInfo>
        <Attr Name="ImportPath" Val="$PPRDIR/../../../trialley/Desktop/LS_CPU_LAB/6_single_cycle_cpu/single_cycle_cpu.xdc"/>
        <Attr Name="ImportTime" Val="1486611786"/>
        <Attr Name="UsedIn" Val="synthesis"/>
        <Attr Name="UsedIn" Val="implementation"/>
      </FileInfo>
    </File>
    <Config>
      <Option Name="ConstrsType" Val="XDC"/>
    </Config>
  </FileSet>
  <FileSet Name="utils" Type="Utils" RelSrcDir="$PSRCDIR/utils_1">
    <Filter Type="Utils"/>
    <Config>
      <Option Name="TopAutoSet" Val="TRUE"/>
    </Config>
  </FileSet>
  <Strategy Version="1" Minor="2">
    <StratHandle Name="Vivado Synthesis Defaults" Flow="Vivado Synthesis 2016"/>
    <Step Id="synth_design"/>
  </Strategy>
</GenRun>
